subprocess_shell/__init__.py
subprocess_shell-1.2.4.dist-info/licenses/LICENSE
subprocess_shell-1.2.4.dist-info/METADATA
subprocess_shell-1.2.4.dist-info/WHEEL
subprocess_shell-1.2.4.dist-info/top_level.txt
subprocess_shell-1.2.4.dist-info/RECORD
