Metadata-Version: 2.4
Name: subprocess_shell
Version: 1.2.4
Summary: A shell for subprocess
Author-email: Andreas Rappold <not_evil@rappold1.at>
License: MIT License
Project-URL: Homepage, https://gitlab.com/notEvil/subprocess_shell
Project-URL: Bug Tracker, https://gitlab.com/notEvil/subprocess_shell/-/issues
Requires-Python: >=3.9
License-File: LICENSE
Provides-Extra: test
Requires-Dist: hypothesis; extra == "test"
Requires-Dist: pytest; extra == "test"
Provides-Extra: all
Requires-Dist: hypothesis; extra == "all"
Requires-Dist: pytest; extra == "all"
Requires-Dist: rich; extra == "all"
Requires-Dist: typer; extra == "all"
Dynamic: license-file
